CHANGES.rst
LICENSE
MANIFEST.in
README.rst
VERSION
requirements.txt
setup.cfg
setup.py
unicore/__init__.py
unicore/__init__.pyc
unicore.languages.egg-info/PKG-INFO
unicore.languages.egg-info/SOURCES.txt
unicore.languages.egg-info/dependency_links.txt
unicore.languages.egg-info/namespace_packages.txt
unicore.languages.egg-info/not-zip-safe
unicore.languages.egg-info/top_level.txt
unicore/languages/__init__.py
unicore/languages/__init__.pyc
unicore/languages/constants.py
unicore/languages/constants.pyc
unicore/languages/tests/test_languages.py
unicore/languages/tests/__pycache__/test_languages.cpython-27-PYTEST.pyc