Metadata-Version: 1.1
Name: unicore.languages
Version: 1.0.0
Summary: Language codes for Universal Core
Home-page: http://github.com/universalcore/unicore.languages
Author: Praekelt Foundation
Author-email: dev@praekelt.com
License: BSD
Keywords: elastic-git,universal,core
Platform: UNKNOWN
Classifier: Programming Language :: Python
Classifier: Framework :: Pyramid
Classifier: Topic :: Internet :: WWW/HTTP
Classifier: Topic :: Internet :: WWW/HTTP :: WSGI :: Application
